cortex/__init__.py
cortex/__version__.py
cortex/api/__init__.py
cortex/api/__main__.py
cortex/api/docs/__init__.py
cortex/api/docs/main.py
cortex/api/docs/meta.py
cortex/api/main.py
cortex/api/routers/__init__.py
cortex/api/routers/consumers/__init__.py
cortex/api/routers/consumers/consumers.py
cortex/api/routers/consumers/groups.py
cortex/api/routers/dashboards/__init__.py
cortex/api/routers/dashboards/dashboards.py
cortex/api/routers/data/__init__.py
cortex/api/routers/data/models.py
cortex/api/routers/data/sources.py
cortex/api/routers/environments.py
cortex/api/routers/metrics.py
cortex/api/routers/preaggregations.py
cortex/api/routers/query_history.py
cortex/api/routers/workspaces.py
cortex/api/schemas/__init__.py
cortex/api/schemas/requests/__init__.py
cortex/api/schemas/requests/agents.py
cortex/api/schemas/requests/consumer/__init__.py
cortex/api/schemas/requests/consumer/consumers.py
cortex/api/schemas/requests/consumer/groups.py
cortex/api/schemas/requests/dashboards.py
cortex/api/schemas/requests/data_models.py
cortex/api/schemas/requests/data_sources.py
cortex/api/schemas/requests/environments.py
cortex/api/schemas/requests/metrics.py
cortex/api/schemas/requests/preaggregations.py
cortex/api/schemas/requests/query_history.py
cortex/api/schemas/requests/workspaces.py
cortex/api/schemas/responses/__init__.py
cortex/api/schemas/responses/consumers/__init__.py
cortex/api/schemas/responses/consumers/consumers.py
cortex/api/schemas/responses/consumers/groups.py
cortex/api/schemas/responses/dashboards.py
cortex/api/schemas/responses/data_models.py
cortex/api/schemas/responses/data_sources.py
cortex/api/schemas/responses/environments.py
cortex/api/schemas/responses/metrics.py
cortex/api/schemas/responses/preaggregations.py
cortex/api/schemas/responses/query_history.py
cortex/api/schemas/responses/validators.py
cortex/api/schemas/responses/workspaces.py
cortex/api/static/redoc.standalone.js
cortex/api/static/swagger-ui-bundle.js
cortex/api/static/swagger-ui.css
telescope_cortex-0.0.1a6.dist-info/METADATA
telescope_cortex-0.0.1a6.dist-info/WHEEL
telescope_cortex-0.0.1a6.dist-info/licenses/LICENSE
telescope_cortex-0.0.1a6.dist-info/RECORD
