Metadata-Version: 2.4
Name: telescope-cortex
Version: 0.0.1a6
Summary: Minimal Headless BI for perfectionists with deadline
License: MIT
License-File: LICENSE
Author: Nilotpal Roychowdhury
Author-email: nilotpal@jointelescope.com
Requires-Python: >=3.12,<3.14
Classifier: License :: OSI Approved :: MIT License
Classifier: Programming Language :: Python :: 3
Classifier: Programming Language :: Python :: 3.12
Classifier: Programming Language :: Python :: 3.13
Provides-Extra: api
Provides-Extra: postgres-pg8000
Requires-Dist: alembic (>=1.16.5,<2.0.0)
Requires-Dist: duckdb (>=1.4.1,<2.0.0)
Requires-Dist: duckdb-engine (>=0.17.0,<0.18.0)
Requires-Dist: fastapi[standard] (>=0.115.8,<0.116.0) ; extra == "api"
Requires-Dist: pg8000 (>=1.30.0,<2.0.0) ; extra == "postgres-pg8000"
Requires-Dist: psycopg[binary,pool] (==3.2.10)
Requires-Dist: pydantic (>=2.12.3,<3.0.0)
Requires-Dist: pymysql[rsa] (>=1.1.2,<2.0.0)
Requires-Dist: python-dotenv (>=1.2.1,<2.0.0)
Requires-Dist: pytz (>=2025.1,<2026.0)
Requires-Dist: redis (>=6.4.0,<7.0.0)
Requires-Dist: rich (>=14.2.0,<15.0.0)
Requires-Dist: scalar-fastapi (>=1.0.3,<2.0.0) ; extra == "api"
Requires-Dist: secweb (>=1.25.2,<2.0.0) ; extra == "api"
Requires-Dist: sqlalchemy (>=2.0.38,<3.0.0)
Requires-Dist: sqlalchemy-bigquery (==1.15.0)
Requires-Dist: uvicorn (>=0.36.1,<0.37.0) ; extra == "api"
